MANIFEST.in
README.rst
setup.py
micral_summary/__init__.py
micral_summary/micral_summary.py
micral_summary/template.docx
micral_summary/version.txt
micral_summary.egg-info/PKG-INFO
micral_summary.egg-info/SOURCES.txt
micral_summary.egg-info/dependency_links.txt
micral_summary.egg-info/not-zip-safe
micral_summary.egg-info/requires.txt
micral_summary.egg-info/top_level.txt
micral_summary/examples/Annealing_twins.jpg
micral_summary/examples/Bronze.jpg
micral_summary/examples/Ductile_iron.jpg
micral_summary/examples/Gray_iron.jpg
micral_summary/examples/Hypoeutectoid_steel.jpg
micral_summary/examples/Malleable_iron.jpg
micral_summary/examples/Martensite.jpg
micral_summary/examples/Pearlite.jpg
micral_summary/examples/Spheroidite.jpg
micral_summary/examples/Superalloy.jpg
micral_summary/examples/bronze.jpg
micral_summary/examples/martensite.jpg
micral_summary/examples/spheroidite.jpg
micral_summary/examples/superalloy.jpg