Metadata-Version: 1.0
Name: micral-summary
Version: 2.0
Summary: User friendly outputing tool for Micral
Home-page: UNKNOWN
Author: Yann LEROY
Author-email: yann.leroy102@orange.fr
License: MIT
Platform: UNKNOWN
